kfslog/kfslog.py
kfslog-3.0.1.dist-info/METADATA
kfslog-3.0.1.dist-info/WHEEL
kfslog-3.0.1.dist-info/RECORD
