Metadata-Version: 2.1
Name: kfslog
Version: 3.0.1
Summary: 
Home-page: https://github.com/9-FS/kfslog
License: MIT
Author: 9FS
Author-email: pray4spam@googlemail.com
Requires-Python: >=3.12.0,<4.0.0
Classifier: License :: OSI Approved :: MIT License
Classifier: Programming Language :: Python :: 3
Classifier: Programming Language :: Python :: 3.12
Requires-Dist: colorama (>=0.4.6,<0.5.0)
Requires-Dist: kfsfstr (>=2.0.0,<3.0.0)
Requires-Dist: result (>=0.16.0,<0.17.0)
Project-URL: Repository, https://github.com/9-FS/kfslog
